LICENSE
MANIFEST.in
NOTICE.md
README.md
setup.cfg
setup.py
spotinst_sdk/__init__.py
spotinst_sdk/aws_elastigroup.py
spotinst_sdk/spotinst_asg.py
spotinst_sdk/spotinst_blue_green_deployment.py
spotinst_sdk/spotinst_deployment_action.py
spotinst_sdk/spotinst_emr.py
spotinst_sdk/spotinst_event_subscription.py
spotinst_sdk/spotinst_functions.py
spotinst_sdk/spotinst_mlb.py
spotinst_sdk/spotinst_ocean.py
spotinst_sdk/spotinst_stateful.py
spotinst_sdk/spotinst_user_mapping.py
spotinst_sdk/version.py
spotinst_sdk.egg-info/PKG-INFO
spotinst_sdk.egg-info/SOURCES.txt
spotinst_sdk.egg-info/dependency_links.txt
spotinst_sdk.egg-info/requires.txt
spotinst_sdk.egg-info/top_level.txt